{
    "chain_name": "beezee",
    "chain_id": "beezee-1",
    "assets": [
        {
            "base": "ibc/689DD6F80E4DBCE14877462B182504037FAEAD0699D5804A7F5CB328D33ED24B",
            "type_asset": "ics20",
            "supply": 1000,
            "ibc": {
                "source_channel": "channel-1",
                "dst_channel": "channel-12",
                "source_denom": "uvdl"
            },
            "traces": [
                {
                    "type": "ibc",
                    "counterparty": {
                        "chain_id": "vidulum-1",
                        "channel_id": "channel-12",
                        "base_denom": "uvdl",
                        "chain_name": "vidulum",
                        "base_supply": 22315473015300
                    },
                    "chain": {
                        "channel_id": "channel-1",
                        "path": "transfer/channel-1/uvdl"
                    }
                }
            ]
        },
        {
            "base": "ibc/ED07A3391A112B175915CD8FAF43A2DA8E4790EDE12566649D0C2F97716B8518",
            "type_asset": "ics20",
            "supply": 11000,
            "description": "The native token of Osmosis",
            "denom_units": [
                {
                    "denom": "uosmo",
                    "exponent": 0,
                    "aliases": []
                },
                {
                    "denom": "osmo",
                    "exponent": 6,
                    "aliases": []
                }
            ],
            "display": "osmo",
            "ibc": {
                "source_channel": "channel-0",
                "dst_channel": "channel-340",
                "source_denom": "uosmo"
            },
            "traces": [
                {
                    "type": "ibc",
                    "counterparty": {
                        "chain_id": "osmosis-1",
                        "channel_id": "channel-340",
                        "base_denom": "uosmo",
                        "chain_name": "osmosis",
                        "base_supply": 617876204337537
                    },
                    "chain": {
                        "channel_id": "channel-0",
                        "path": "transfer/channel-0/uosmo"
                    }
                }
            ]
        },
        {
            "base": "ubze",
            "type_asset": "sdk.coin",
            "supply": 271438252423464
        }
    ]
}